flextape/__init__.py
flextape/ready_request.py
FlexTape-0.1.0.dist-info/LICENSE
FlexTape-0.1.0.dist-info/METADATA
FlexTape-0.1.0.dist-info/WHEEL
FlexTape-0.1.0.dist-info/top_level.txt
FlexTape-0.1.0.dist-info/RECORD
