Metadata-Version: 2.1
Name: FlexTape
Version: 0.1.0
Summary: Python library to download multiple images at once with a request limit.
Author: Duckling Dean
Author-email: duckling.dean@proton.me
License-File: LICENSE
Requires-Dist: requests <3.0.0,>=2.32.2
Requires-Dist: fake-useragent ==1.5.1
